{
  "type": "Epistola",
  "title": "EPISTOLA Emery R. Walker, Jr.",
  "contributor": "Emery R. Walker, Jr.",
  "html": "<link rel=\"type\" href=\"Epistola\"><h1 data-rel=\"title\">EPISTOLA <span data-rel=\"contributor\">Emery R. Walker, Jr.</span></h1>\n<p>Here are a few palindromes not on Mr. Lederer's list\n[XI,3]:</p>\n<blockquote>\n<p>Pa's a sap.<br>\nWon't lovers revolt now?<br>\nA dog!  A panic in a pagoda.<br>\nDraw putrid dirt upward.<br>\nPoor Dan is in a droop.<br>\nZeus was deified, saw Suez.<br>\nI roamed under it as a tired nude Maori.<br>\nDraw no dray a yard onward.<br>\n“Do nine men interpret?”  “Nine men,” I nod.</p>\n</blockquote>\n<p><em>[Emery R. Walker, Jr., Claremont, California]</em></p>\n<h2></h2>",
  "preview": "<link rel=\"type\" href=\"Epistola\"> <h1 data-rel=\"title\">EPISTOLA <span data-rel=\"contributor\">Emery R. Walker, Jr.</span></h1> <p>Here are a few palindromes not on Mr. Lederer's list\n[XI,3]:</p> <blockquote>\n<p>Pa's a sap.<br>\nWon't lovers revolt now?<br>\nA dog!  A panic in a pagoda.<br>\nDraw putrid dirt upward.<br>\nPoor Dan is in a droop.<br>\nZeus was deified, saw Suez.<br>\nI roamed under it as a tired nude Maori.<br>\nDraw no dray a yard onward.<br>\n“Do nine men interpret?”  “Nine men,” I nod.</p>\n</blockquote> <p><em>[Emery R. Walker, Jr., Claremont, California]</em></p> <h2></h2>"
}