{
  "type": "Epistola",
  "title": "EPISTOLA Garretta E. Howard",
  "contributor": "Garretta E. Howard",
  "html": "<link rel=\"type\" href=\"Epistola\"><h1 data-rel=\"title\">EPISTOLA <span data-rel=\"contributor\">Garretta E. Howard</span></h1>\n<p>The onomatoplazia of <em>inflammable</em> is so common\nthat <em>flammable</em>, or even <em>flamable</em> is now commonly\nsubstituted, especially on trucks.</p>\n<p><em>[Garretta E. Howard, Del Rio, Texas]</em></p>\n<h2></h2>",
  "preview": "<link rel=\"type\" href=\"Epistola\"> <h1 data-rel=\"title\">EPISTOLA <span data-rel=\"contributor\">Garretta E. Howard</span></h1> <p>The onomatoplazia of <em>inflammable</em> is so common\nthat <em>flammable</em>, or even <em>flamable</em> is now commonly\nsubstituted, especially on trucks.</p> <p><em>[Garretta E. Howard, Del Rio, Texas]</em></p> <h2></h2>"
}