{
  "type": "Epistola",
  "title": "EPISTOLA Bernard Witlieb",
  "contributor": "Bernard Witlieb",
  "html": "<link rel=\"type\" href=\"Epistola\"><h1 data-rel=\"title\">EPISTOLA <span data-rel=\"contributor\">Bernard Witlieb</span></h1>\n<p>Amy Stoller's letter [XVII,1] identifies Jerry\nLeiber and Mike Stoller as the creators of “Is That\nAll There Is?”  She has inadvertently slighted that\ngiant of Tin Pan Allee-Thomas Mann.  In <em>Disillusionment</em>\n(1897), an old man in Venice recalls the\npast:</p>\n<blockquote>\n<p>“So this,” I thought, “is a fire.  This is what it is\nlike to have the house on fire.  Is this all there is\nto it?”</p>\n<p>Then, remembering being jilted, he asks,\n“Is this all?”</p>\n<p>Finally, he expects death to be</p>\n<p>“that last disappointment....  So this is the\ngreat experience—well, what of it?  What is it after\nall?”</p>\n</blockquote>\n<p>And all these years critics have jeered at\nThomas's brother Heinrich as the great popularizer!</p>\n<p><em>[Bernard Witlieb, White Plains, New York]</em></p>\n<h1></h1>",
  "preview": "<link rel=\"type\" href=\"Epistola\"> <h1 data-rel=\"title\">EPISTOLA <span data-rel=\"contributor\">Bernard Witlieb</span></h1> <p>Amy Stoller's letter [XVII,1] identifies Jerry\nLeiber and Mike Stoller as the creators of “Is That\nAll There Is?”  She has inadvertently slighted that\ngiant of Tin Pan Allee-Thomas Mann.  In <em>Disillusionment</em>\n(1897), an old man in Venice recalls the\npast:</p> <blockquote>\n<p>“So this,” I thought, “is a fire.  This is what it is\nlike to have the house on fire.  Is this all there is\nto it?”</p>\n<p>Then, remembering being jilted, he asks,\n“Is this all?”</p>\n<p>Finally, he expects death to be</p>\n<p>“that last disappointment....  So this is the\ngreat experience—well, what of it?  What is it after\nall?”</p>\n</blockquote> <p>And all these years critics have jeered at\nThomas's brother Heinrich as the great popularizer!</p> <p><em>[Bernard Witlieb, White Plains, New York]</em></p>"
}