{
  "type": "Epistola",
  "title": "EPISTOLA Morrie K. Blumberg",
  "contributor": "Morrie K. Blumberg",
  "html": "<link rel=\"type\" href=\"Epistola\"><h1 data-rel=\"title\">EPISTOLA <span data-rel=\"contributor\">Morrie K. Blumberg</span></h1>\n<p>The Editor's comments on “...prejudice against Negroes in many Western societies...” [XXI, 3, 9] were apt but somewhat incomplete. I saw equally severe prejudice against people of darker skin, often including Negroes, by non-Whites in two major Asian countries in which I worked (1968-70, 1978-83) and in fourteen sub-Saharan African countries in which I worked (1972-74). Bigotry against Blacks, sadly, is not confined to Western societies.</p>\n<p><em>[Morrie K. Blumberg, Foreign Service Office, Ret. U.S. Agency for Int'l. Development Albuquerque]</em></p>\n<h2></h2>",
  "preview": "<link rel=\"type\" href=\"Epistola\"> <h1 data-rel=\"title\">EPISTOLA <span data-rel=\"contributor\">Morrie K. Blumberg</span></h1> <p>The Editor's comments on “...prejudice against Negroes in many Western societies...” [XXI, 3, 9] were apt but somewhat incomplete. I saw equally severe prejudice against people of darker skin, often including Negroes, by non-Whites in two major Asian countries in which I worked (1968-70, 1978-83) and in fourteen sub-Saharan African countries in which I worked (1972-74). Bigotry against Blacks, sadly, is not confined to Western societies.</p> <p><em>[Morrie K. Blumberg, Foreign Service Office, Ret. U.S. Agency for Int'l. Development Albuquerque]</em></p> <h2></h2>"
}