{
  "type": "Epistola",
  "title": "EPISTOLA Jon Simpson",
  "contributor": "Jon Simpson",
  "html": "<link rel=\"type\" href=\"Epistola\"><h1 data-rel=\"title\">EPISTOLA <span data-rel=\"contributor\">Jon Simpson</span></h1>\n<p>[Barry Popik, the indefatigable word-origins researcher, has found a letter to the <em>New York Times</em> of 18 March 1946 (and a similar letter to <em>Life</em> magazine of the same date) that makes reference to this drawing and suggests that the name used for it, “Mr. Chad” (not just “Chad”), came from the nickname of a REME (Royal Electrical and Mechanical Engineers) training unit, popularly known as 'Chad's Temple'. According to the <em>Life</em> letter, he was also known as “Flywheel,” “Doomie” or “The Goon” in the RAF; “Foo” or “The Watcher” in the Royal Navy; “Clem,” “Private Snoops,” or “The Jeep” in the army.—Ed.]</p>\n<p>Nick Humez's Classical Blather is always very entertaining. I have a couple of quibbles, however, with his latest article on “-ists, -ites, and Other Ends” (XXVI No 2):</p>\n<p>1. “<em>sitar</em> is cognate with Greek <em>kithara</em>”</p>\n<p>Hindi <em>sitar</em> comes from Persian <em>si</em> (three) + <em>tar</em> (string), whereas <em>kithara</em> probably refers to a cavity.</p>\n<p>2. “So we speak of <em>suffragettes</em> (called <em>suffragists</em> in England)”</p>\n<p>The English surely use both forms, <em>-ette</em> providing negative connotations of feminine militancy, and <em>-ist</em> describing any advocate of suffrage.</p>\n<p>He deserves a medal for working on a much needed index for volumes 7-25. I can hardly wait for its publication.</p>\n<p><em>[Jon Simpson, Quispamsis, New Brunswick, <a href=\"mailto:simpsons@nbnet.nb.ca\">simpsons@nbnet.nb.ca</a>]</em></p>\n<h2></h2>",
  "preview": "<link rel=\"type\" href=\"Epistola\"> <h1 data-rel=\"title\">EPISTOLA <span data-rel=\"contributor\">Jon Simpson</span></h1> <p>[Barry Popik, the indefatigable word-origins researcher, has found a letter to the <em>New York Times</em> of 18 March 1946 (and a similar letter to <em>Life</em> magazine of the same date) that makes reference to this drawing and suggests that the name used for it, “Mr. Chad” (not just “Chad”), came from the nickname of a REME (Royal Electrical and Mechanical Engineers) training unit, popularly known as 'Chad's Temple'. According to the <em>Life</em> letter, he was also known as “Flywheel,” “Doomie” or “The Goon” in the RAF; “Foo” or “The Watcher” in the Royal Navy; “Clem,” “Private Snoops,” or “The Jeep” in the army.—Ed.]</p> <p>Nick Humez's Classical Blather is always very entertaining. I have a couple of quibbles, however, with his latest article on “-ists, -ites, and Other Ends” (XXVI No 2):</p> <p>1. “<em>sitar</em> is cognate with Greek <em>kithara</em>”</p> <p>Hindi <em>sitar</em> comes from Persian <em>si</em> (three) + <em>tar</em> (string), whereas <em>kithara</em> probably refers to a cavity.</p>"
}