{
  "type": "Epistola",
  "title": "EPISTOLA Nancy Birkrem",
  "contributor": "Nancy Birkrem",
  "html": "<link rel=\"type\" href=\"Epistola\"><h1 data-rel=\"title\">EPISTOLA <span data-rel=\"contributor\">Nancy Birkrem</span></h1>\n<p>Your call for words that deserve to be resurrected came at a propitious time for me. Just yesterday I found <em>chalybeate,</em> tucked between <em>receivable</em> and <em>neutrality</em> in list no. 35 of William T. Adams' “A spelling-book for advanced classes” (c1868).</p>\n<p><em>Webster's New International Dictionary,</em> 2nd ed., unabridged (1944) defines <em>chalybeate</em> as “impregnated with salts of iron; having a taste due to iron”. In those communities with fluoridated water any underlying taste of iron may be muted, but I'm sure there are still many to whom its distinctive qualities are well known.</p>\n<p><em>[Nancy Birkrem, Rare Books Librarian, Mount Holyoke College, South Hadley, Massachusetts]</em></p>\n<h2></h2>",
  "preview": "<link rel=\"type\" href=\"Epistola\"> <h1 data-rel=\"title\">EPISTOLA <span data-rel=\"contributor\">Nancy Birkrem</span></h1> <p>Your call for words that deserve to be resurrected came at a propitious time for me. Just yesterday I found <em>chalybeate,</em> tucked between <em>receivable</em> and <em>neutrality</em> in list no. 35 of William T. Adams' “A spelling-book for advanced classes” (c1868).</p> <p><em>Webster's New International Dictionary,</em> 2nd ed., unabridged (1944) defines <em>chalybeate</em> as “impregnated with salts of iron; having a taste due to iron”. In those communities with fluoridated water any underlying taste of iron may be muted, but I'm sure there are still many to whom its distinctive qualities are well known.</p> <p><em>[Nancy Birkrem, Rare Books Librarian, Mount Holyoke College, South Hadley, Massachusetts]</em></p> <h2></h2>"
}