{
  "type": "Issue",
  "volume": "26",
  "number": "4",
  "hasPart": [
    "v26_4_1",
    "v26_4_2",
    "v26_4_3",
    "v26_4_4",
    "v26_4_5",
    "v26_4_6",
    "v26_4_7",
    "v26_4_8",
    "v26_4_9",
    "v26_4_10",
    "v26_4_11",
    "v26_4_12",
    "v26_4_13",
    "v26_4_14",
    "v26_4_15",
    "v26_4_16",
    "v26_4_17",
    "v26_4_18",
    "v26_4_19",
    "v26_4_20",
    "v26_4_21",
    "v26_4_22",
    "v26_4_23",
    "v26_4_24",
    "v26_4_25",
    "v26_4_26"
  ],
  "title": "VOL XXVI, No 4",
  "season": "Spring",
  "year": 2000
}