{
  "type": "Epistola",
  "title": "EPISTOLA Barbara Blankenship",
  "contributor": "Barbara Blankenship",
  "html": "<link rel=\"type\" href=\"Epistola\"><h1 data-rel=\"title\">EPISTOLA <span data-rel=\"contributor\">Barbara Blankenship</span></h1>\n<p>Re p. 7 of VERBATIM XXVII/4, I don't have a proper source for this observation, but <em>Cackylacky</em> sounds suspiciously like the German word <em>Kakerlaken</em> “cockroaches.” (And the etymology of <em>Kakerlak</em> bears looking into. Was it, like the English <em>cockroach,</em> borrowed from Spanish <em>cucaracha</em> and folk-etymologized into its current form?)</p>\n<p><em>[Barbara Blankenship, Linguistics, UCLA]</em></p>",
  "preview": "<link rel=\"type\" href=\"Epistola\"> <h1 data-rel=\"title\">EPISTOLA <span data-rel=\"contributor\">Barbara Blankenship</span></h1> <p>Re p. 7 of VERBATIM XXVII/4, I don't have a proper source for this observation, but <em>Cackylacky</em> sounds suspiciously like the German word <em>Kakerlaken</em> “cockroaches.” (And the etymology of <em>Kakerlak</em> bears looking into. Was it, like the English <em>cockroach,</em> borrowed from Spanish <em>cucaracha</em> and folk-etymologized into its current form?)</p> <p><em>[Barbara Blankenship, Linguistics, UCLA]</em></p>"
}