{
  "type": "Epistola",
  "title": "EPISTOLA Keen Rafferty",
  "contributor": "Keen Rafferty",
  "html": "<link rel=\"type\" href=\"Epistola\"><h1 data-rel=\"title\">EPISTOLA <span data-rel=\"contributor\">Keen Rafferty</span></h1>\n<p>I regret that in your “Noun Overuse Phenomenon Article” by Mr. Bruce Price [II, 4] you failed to include the newspaper headline, “Jones Hits Fish Sale Ban Repealer,” although the omission is understandable, since it never got in the paper.</p>\n<p>As the former head of the copydesk of <em>The Baltimore Evening Sun</em> (in the 1930's), I have been waiting for an article about <em>literally</em>. “The American destroyer was literally disemboweled” was a sentence in an Associated Press dispatch during World War II. A recent book of mine cites “The Packers Literally Exploded in the Fourth Quarter.” Even more bloody was a politician's boast, “I literally tore that fellow apart, eh?”</p>\n<p>In television news recently towns have been <em>literally</em> erased from the map, the English language has been <em>literally</em> murdered (could it truly be?), and spectators at a hockey game <em>literally</em> tore the place to shreds.</p>\n<p><em>[Keen Rafferty, Emeritus Professor of Journalism The University of New Mexico]</em></p>\n<h1></h1>",
  "preview": "<link rel=\"type\" href=\"Epistola\"> <h1 data-rel=\"title\">EPISTOLA <span data-rel=\"contributor\">Keen Rafferty</span></h1> <p>I regret that in your “Noun Overuse Phenomenon Article” by Mr. Bruce Price [II, 4] you failed to include the newspaper headline, “Jones Hits Fish Sale Ban Repealer,” although the omission is understandable, since it never got in the paper.</p> <p>As the former head of the copydesk of <em>The Baltimore Evening Sun</em> (in the 1930's), I have been waiting for an article about <em>literally</em>. “The American destroyer was literally disemboweled” was a sentence in an Associated Press dispatch during World War II. A recent book of mine cites “The Packers Literally Exploded in the Fourth Quarter.” Even more bloody was a politician's boast, “I literally tore that fellow apart, eh?”</p> <p>In television news recently towns have been <em>literally</em> erased from the map, the English language has been <em>literally</em> murdered (could it truly be?), and spectators at a hockey game <em>literally</em> tore the place to shreds.</p> <p><em>[Keen Rafferty, Emeritus Professor of Journalism The University of New Mexico]</em></p>"
}