{
  "type": "Issue",
  "volume": "4",
  "number": "4",
  "hasPart": [
    "v4_4_1",
    "v4_4_2",
    "v4_4_3",
    "v4_4_4",
    "v4_4_5",
    "v4_4_6",
    "v4_4_7",
    "v4_4_8",
    "v4_4_9",
    "v4_4_10",
    "v4_4_11",
    "v4_4_12",
    "v4_4_13",
    "v4_4_14",
    "v4_4_15",
    "v4_4_16",
    "v4_4_17",
    "v4_4_18",
    "v4_4_19",
    "v4_4_20",
    "v4_4_21",
    "v4_4_22",
    "v4_4_23",
    "v4_4_24",
    "v4_4_25",
    "v4_4_26",
    "v4_4_27",
    "v4_4_28",
    "v4_4_29",
    "v4_4_30",
    "v4_4_31",
    "v4_4_32",
    "v4_4_33",
    "v4_4_34",
    "v4_4_35",
    "v4_4_36",
    "v4_4_37"
  ],
  "title": "Vol IV, No 4 [September 1977]",
  "season": "Spring",
  "year": 1978
}