{
  "type": "Issue",
  "volume": "5",
  "number": "2",
  "hasPart": [
    "v5_2_1",
    "v5_2_2",
    "v5_2_3",
    "v5_2_4",
    "v5_2_5",
    "v5_2_6",
    "v5_2_7",
    "v5_2_8",
    "v5_2_9",
    "v5_2_10",
    "v5_2_11",
    "v5_2_12",
    "v5_2_13",
    "v5_2_14",
    "v5_2_15",
    "v5_2_16",
    "v5_2_17",
    "v5_2_18",
    "v5_2_19",
    "v5_2_20",
    "v5_2_21",
    "v5_2_22",
    "v5_2_23",
    "v5_2_24",
    "v5_2_25",
    "v5_2_26",
    "v5_2_27",
    "v5_2_28",
    "v5_2_29",
    "v5_2_30",
    "v5_2_31",
    "v5_2_32",
    "v5_2_33",
    "v5_2_34",
    "v5_2_35",
    "v5_2_36"
  ],
  "title": "VOL V, No 2 [September, 1978]",
  "season": "Autumn",
  "year": 1978
}