{
  "type": "Article",
  "title": "Copper Beeches",
  "author": "Padraic Colum",
  "location": "",
  "html": "<link rel=\"type\" href=\"Article\"><h1 data-rel=\"title\">Copper Beeches</h1>\n<p><em><span data-rel=\"author\">Padraic Colum</span> <span data-rel=\"location\"></span></em></p>\n<p>Talmudic in their alienness<br>\nThe Copper Beeches are beside<br>\nThe Willow, Ash and Sycamore—<br>\nDark, ponderous trees.</p>\n<p>The Willow, Ash and Sycamore<br>\nProfess the green.  And them beside,<br>\nWith branches close around dark stems<br>\nAnd leaves like burnished metal, dark—<br>\nUnordained trees.</p>\n<p>Alien as minds that pondered on<br>\nThe letters twelve and forty-two,<br>\nAnd in their inner depths pronounced<br>\nThe name that's figured in the great<br>\nTetragrammaton.</p>\n<p>The Copper Beeches spread beside<br>\nThe Willow, Ash and Sycamore,<br>\nAlien, but more—discordant they—<br>\nDiscordant as the metal clang<br>\nAgainst the lutes, the flutes, the chimes—<br>\nDark ponderous trees!</p>\n<h1></h1>",
  "preview": "<link rel=\"type\" href=\"Article\"> <h1 data-rel=\"title\">Copper Beeches</h1> <p><em><span data-rel=\"author\">Padraic Colum</span> <span data-rel=\"location\"></span></em></p> <p>Talmudic in their alienness<br>\nThe Copper Beeches are beside<br>\nThe Willow, Ash and Sycamore—<br>\nDark, ponderous trees.</p> <p>The Willow, Ash and Sycamore<br>\nProfess the green.  And them beside,<br>\nWith branches close around dark stems<br>\nAnd leaves like burnished metal, dark—<br>\nUnordained trees.</p> <p>Alien as minds that pondered on<br>\nThe letters twelve and forty-two,<br>\nAnd in their inner depths pronounced<br>\nThe name that's figured in the great<br>\nTetragrammaton.</p>"
}