{
  "type": "Article",
  "title": "Unlikely? That's the Name of the Game",
  "author": "Warren Tupper Way",
  "location": "Wayzata, Minnesota",
  "html": "<link rel=\"type\" href=\"Article\"><h1 data-rel=\"title\">Unlikely? That's the Name of the Game</h1>\n<p><em><span data-rel=\"author\">Warren Tupper Way</span> <span data-rel=\"location\">Wayzata, Minnesota</span></em></p>\n<p><em>unstrung</em> a naked guitar<br>\n<em>unlikely</em> you aren't disliked, but “'people don't  give you no respect”<br>\n<em>unaccustomed</em> smuggled<br>\n<em>uninspired</em> an empty balloon<br>\n<em>undulation</em> faint praise<br>\n<em>unbalanced</em> a neurotic bookkeeper<br>\n<em>unremitting</em> slow pay<br>\n<em>ungainly</em> just got back to the line of scrimmage<br>\n<em>unbecoming</em> won't be home for Christmas<br>\n<em>unlocked</em> Samson<br>\n<em>uncanny</em> no toilets<br>\n<em>untold</em> the Liberty Bell<br>\n<em>unadulterated</em> a chaste wife<br>\n<em>unmatched</em> fire by friction<br>\n<em>unfulfilled</em> no help for your two pair<br>\n<em>unbidden</em> a three-point bridge hand<br>\n<em>untoward</em> backwards<br>\n<em>unjust</em> not quite<br>\n<em>unlettered</em> gets no mail<br>\n<em>unspoken</em> comes with disc wheels<br>\n<em>unprepossessing</em> owner of a brand new car<br>\n<em>unTIMEly</em> U.S. News &amp; World Report<br>\n<em>unhorse</em> no longer has a sore throat<br>\n<em>uncooperative</em> a company store<br>\n<em>unincorporated</em> a very small labor union<br>\n<em>unwashed</em> money that doesn't go to the “family” until Monday<br>\n<em>unwanted</em> already in prison<br>\n<em>unwilling</em> will die intestate<br>\n<em>unfortunate</em> disinherited by a wealthy relative<br>\n<em>unfriendly</em> a former Quaker<br>\n<em>untreated</em> an empty Halloween bag<br>\n<em>unavailing</em> when you plead to Noah Vail<br>\n<em>unfailing</em> made a “D” average</p>",
  "preview": "<link rel=\"type\" href=\"Article\"> <h1 data-rel=\"title\">Unlikely? That's the Name of the Game</h1> <p><em><span data-rel=\"author\">Warren Tupper Way</span> <span data-rel=\"location\">Wayzata, Minnesota</span></em></p> <p><em>unstrung</em> a naked guitar<br>\n<em>unlikely</em> you aren't disliked, but “'people don't  give you no respect”<br>\n<em>unaccustomed</em> smuggled<br>\n<em>uninspired</em> an empty balloon<br>\n<em>undulation</em> faint praise<br>\n<em>unbalanced</em> a neurotic bookkeeper<br>\n<em>unremitting</em> slow pay<br>\n<em>ungainly</em> just got back to the line of scrimmage<br>\n<em>unbecoming</em> won't be home for Christmas<br>\n<em>unlocked</em> Samson<br>\n<em>uncanny</em> no toilets<br>\n<em>untold</em> the Liberty Bell<br>\n<em>unadulterated</em> a chaste wife<br>\n<em>unmatched</em> fire by friction<br>\n<em>unfulfilled</em> no help for your two pair<br>\n<em>unbidden</em> a three-point bridge hand<br>\n<em>untoward</em> backwards<br>\n<em>unjust</em> not quite<br>\n<em>unlettered</em> gets no mail<br>\n<em>unspoken</em> comes with disc wheels<br>\n<em>unprepossessing</em> owner of a brand new car<br>\n<em>unTIMEly</em> U.S. News &amp; World Report<br>\n<em>unhorse</em> no longer has a sore throat<br>\n<em>uncooperative</em> a company store<br>\n<em>unincorporated</em> a very small labor union<br>\n<em>unwashed</em> money that doesn't go to the “family” until Monday<br>\n<em>unwanted</em> already in prison<br>\n<em>unwilling</em> will die intestate<br>\n<em>unfortunate</em> disinherited by a wealthy relative<br>\n<em>unfriendly</em> a former Quaker<br>\n<em>untreated</em> an empty Halloween bag<br>\n<em>unavailing</em> when you plead to Noah Vail<br>\n<em>unfailing</em> made a “D” average</p>"
}