{
  "type": "Epistola",
  "title": "EPISTOLA T. S. Terrill",
  "contributor": "T. S. Terrill",
  "html": "<link rel=\"type\" href=\"Epistola\"><h1 data-rel=\"title\">EPISTOLA <span data-rel=\"contributor\">T. S. Terrill</span></h1>\n<p>In response to Sgt. Maj. Dan Cragg's belief that a 1907\nreference to “Bucket, G.I. on strap near axle under body”\nsubstantiates his contention that <em>Gl</em> means 'galvanized iron,'\nI suggest that if the Army had been acting true to form (in\nbeing so slow to change its ways) those buckets would have\nbeen wooden.</p>\n<p>When I was a flying cadet at Randolph/Kelly Fields in\n'34/'35, we referred to enlisted men as <em>GI men</em>.</p>\n<p><em>[T. S. Terrill, Carlsbad, California]</em></p>\n<h2></h2>",
  "preview": "<link rel=\"type\" href=\"Epistola\"> <h1 data-rel=\"title\">EPISTOLA <span data-rel=\"contributor\">T. S. Terrill</span></h1> <p>In response to Sgt. Maj. Dan Cragg's belief that a 1907\nreference to “Bucket, G.I. on strap near axle under body”\nsubstantiates his contention that <em>Gl</em> means 'galvanized iron,'\nI suggest that if the Army had been acting true to form (in\nbeing so slow to change its ways) those buckets would have\nbeen wooden.</p> <p>When I was a flying cadet at Randolph/Kelly Fields in\n'34/'35, we referred to enlisted men as <em>GI men</em>.</p> <p><em>[T. S. Terrill, Carlsbad, California]</em></p> <h2></h2>"
}