{
  "type": "Epistola",
  "title": "EPISTOLA David L. Gold",
  "contributor": "David L. Gold",
  "html": "<link rel=\"type\" href=\"Epistola\"><h1 data-rel=\"title\">EPISTOLA <span data-rel=\"contributor\">David L. Gold</span></h1>\n<p>I agree with Charles Bremer [IV, 2] that “unfortunately,\nour language in its present state is far from an ideal system of\nsymbols, growing as it has from an array of northern European\nand Romance languages with a sprinkling of American Indian,\nYiddish, and a few dozen other languages” and that “therefore,\nsteps must be taken now to purify and distill our language...”\nAs a first step, I propose the removal of such foreignisms as\n<em>American, international, language, eventual, means, people,\nexchange, idea, mutual, unfortunate, present, state, ideal, system,\nsymbol, array, European, Romance, Indian, dozen, mixture,\ntend, develop, extensive, lexicon, complicate, degree,\nendanger, use, purify, distill, accurate, country, effort, communication,\ninterest, support, Charles, city, and Oregon</em> (all taken\nfrom his letter).</p>\n<p><em>[David L. Gold, University of Haifa]</em></p>\n<h1></h1>",
  "preview": "<link rel=\"type\" href=\"Epistola\"> <h1 data-rel=\"title\">EPISTOLA <span data-rel=\"contributor\">David L. Gold</span></h1> <p>I agree with Charles Bremer [IV, 2] that “unfortunately,\nour language in its present state is far from an ideal system of\nsymbols, growing as it has from an array of northern European\nand Romance languages with a sprinkling of American Indian,\nYiddish, and a few dozen other languages” and that “therefore,\nsteps must be taken now to purify and distill our language...”\nAs a first step, I propose the removal of such foreignisms as\n<em>American, international, language, eventual, means, people,\nexchange, idea, mutual, unfortunate, present, state, ideal, system,\nsymbol, array, European, Romance, Indian, dozen, mixture,\ntend, develop, extensive, lexicon, complicate, degree,\nendanger, use, purify, distill, accurate, country, effort, communication,\ninterest, support, Charles, city, and Oregon</em> (all taken\nfrom his letter).</p> <p><em>[David L. Gold, University of Haifa]</em></p> <h1></h1>"
}