{
  "type": "Article",
  "title": "Pairing Pairs No. 9",
  "author": "The clues are given in items lettered (a-z); the\nanswers are given in the numbered items",
  "location": "which must be\nmatched with each other to solve the clues.  In some cases, a\nnumbered item may be used more than once, and some clues\nmay require more than two answer items; but after all of the\nmatchings have been completed, one numbered item will\nremain unmatched, and that is the correct answer.  Our answer\nis the only correct one.  The solution will be published in the\nnext issue of",
  "html": "<link rel=\"type\" href=\"Article\"><h1 data-rel=\"title\">Pairing Pairs No. 9</h1>\n<p><em><span data-rel=\"author\">The clues are given in items lettered (a-z); the\nanswers are given in the numbered items</span> <span data-rel=\"location\">which must be\nmatched with each other to solve the clues.  In some cases, a\nnumbered item may be used more than once, and some clues\nmay require more than two answer items; but after all of the\nmatchings have been completed, one numbered item will\nremain unmatched, and that is the correct answer.  Our answer\nis the only correct one.  The solution will be published in the\nnext issue of</span></em> VERBATIM.</p>\n<p>(a). Shoes that give some young girls a real lift.<br>\n(b). Hearty contingent from New York City?<br>\n(c). He gets only the sweet he merits.<br>\n(d). Dame Sheep has it all together.<br>\n(e). Shadow boxing?<br>\n(f). Okay—he has the price of a ticket.<br>\n(g). Is <em>The Birds</em> treacherous?<br>\n(h). Play bridge to become aroused?<br>\n(i). Special device for watching Persian fairies<br>\n(j). Defendant opposed to ordinary squabble.<br>\n(k). Doubly contemptible musical instrument.<br>\n(l). Slippery scene.<br>\n(m). Naval person.<br>\n(n). Alley's just dessert.<br>\n(o). Forget to put out the cat.<br>\n(p). Where they wait for the flowers to grow.<br>\n(q). Marcel reported heavily Zeus had it with Leda.<br>\n(r). Impressionable leather pendulum.<br>\n(s). Flagg or nut?<br>\n(t). Taxi queue at night club.<br>\n(u). Did Porter know film director?<br>\n(v). Cockney camp follower to ask for a fight.<br>\n(w). Patch.<br>\n(x). Has it rung up for him?<br>\n(y). Order of the day.<br>\n(z). Swindler leads broker a merry dance.<br>\n(1). Apple.<br>\n(2). Array.<br>\n(3). Baba.<br>\n(4). Base.<br>\n(5). Belly.<br>\n(6). Cab.<br>\n(7). Combat.<br>\n(8). Con.<br>\n(9). Corps.<br>\n(10). Dancer.<br>\n(11). Dessert.<br>\n(12). Dutch.<br>\n(13). Easily.<br>\n(14). Enough.<br>\n(15). Ewe.<br>\n(16). Fare.<br>\n(17). Feinting.<br>\n(18). File.<br>\n(19). Four.<br>\n(20). Fowl.<br>\n(21). Gardens.<br>\n(22). Hazel.<br>\n(23). Jacob's.<br>\n(24). Jane.<br>\n(25). Just.<br>\n(26). Knighted:<br>\n(27). Ladder.<br>\n(28). Man.<br>\n(29). Mary.<br>\n(30). Nocturnal.<br>\n(31). Omission.<br>\n(32). Ophuls.<br>\n(33). Order.<br>\n(34). Peri.<br>\n(35). Pie.<br>\n(36). Plain.<br>\n(37). Play.<br>\n(38). Queue.<br>\n(39). Rum.<br>\n(40). Scope.<br>\n(41). Ship.<br>\n(42). Show.<br>\n(43). Slide.<br>\n(44). Spell.<br>\n(45). Suede.<br>\n(46). Swans.<br>\n(47). Tango.<br>\n(48). Tiff.<br>\n(49). Vile.<br>\n(50). Weigh.<br>\n(51). Which.</p>\n<p>Winners will receive one of the following: the Collector's\nEdition of Thomas H. Middleton's <em>Light Refractions</em> (retail\nvalue, $30 or £15); <em>English English</em> by Norman W. Schur\n(retail value, $24.95 or £12.50); three copies of <em>Wordsmanship</em>,\nby Claurène duGran (retail value, $29.85 or £14.85); twelve\ncopies of <em>Definitive Quotations</em>, by John Ferguson (retail value,\n$35.40 or 18); <em>Word for Word</em>, by Edward C. Pinkerton (retail\nvalue, $39.95 or £20); four one-year subscriptions to VERBATIM\n(retail value, $30 or £15); any two of the follwing: <em>Verbatim\nVolumes I &amp; II, Verbatim Volumes III &amp; IV, Verbatim Volumes\nV &amp; VI, Verbatim Index: Volumes I-VI;</em> or a credit of $25 or\n£12.50 towards the purchase of any other title or titles offered\nin the VERBATIM Book Club Catalogue.</p>\n<p>Those living in the U.K., Europe, the Middle East, or\nNorth Africa should send their answers to VERBATIM, 2 Market\nSquare, Aylesbury, Bucks, England.  All others should send\nthem to VERBATIM, Essex, CT 06426, U.S.A.</p>\n<p><em>You need send only the correct solution, not the answers to\nall of the clues.  Please indicate your choice of prize along with\nyour answer</em>.</p>\n<p><em>N.B.:</em> To allow for the sloth of the various postal systems\nand to make it fairer for those residing far from either office,\nwe shall arrange to collect correct answers for 21 days, starting\nwith the day the first correct answer is received, and to draw\none winner from each office.</p>",
  "preview": "<link rel=\"type\" href=\"Article\"> <h1 data-rel=\"title\">Pairing Pairs No. 9</h1> <p><em><span data-rel=\"author\">The clues are given in items lettered (a-z); the\nanswers are given in the numbered items</span> <span data-rel=\"location\">which must be\nmatched with each other to solve the clues.  In some cases, a\nnumbered item may be used more than once, and some clues\nmay require more than two answer items; but after all of the\nmatchings have been completed, one numbered item will\nremain unmatched, and that is the correct answer.  Our answer\nis the only correct one.  The solution will be published in the\nnext issue of</span></em> VERBATIM.</p> <p>(a). Shoes that give some young girls a real lift.<br>\n(b). Hearty contingent from New York City?<br>\n(c). He gets only the sweet he merits.<br>\n(d). Dame Sheep has it all together.<br>\n(e). Shadow boxing?<br>\n(f). Okay—he has the price of a ticket.<br>\n(g). Is <em>The Birds</em> treacherous?<br>\n(h). Play bridge to become aroused?<br>\n(i). Special device for watching Persian fairies<br>\n(j). Defendant opposed to ordinary squabble.<br>\n(k). Doubly contemptible musical instrument.<br>\n(l). Slippery scene.<br>\n(m). Naval person.<br>\n(n). Alley's just dessert.<br>\n(o). Forget to put out the cat.<br>\n(p). Where they wait for the flowers to grow.<br>\n(q). Marcel reported heavily Zeus had it with Leda.<br>\n(r). Impressionable leather pendulum.<br>\n(s). Flagg or nut?<br>\n(t). Taxi queue at night club.<br>\n(u). Did Porter know film director?<br>\n(v). Cockney camp follower to ask for a fight.<br>\n(w). Patch.<br>\n(x). Has it rung up for him?<br>\n(y). Order of the day.<br>\n(z). Swindler leads broker a merry dance.<br>\n(1). Apple.<br>\n(2). Array.<br>\n(3). Baba.<br>\n(4). Base.<br>\n(5). Belly.<br>\n(6). Cab.<br>\n(7). Combat.<br>\n(8). Con.<br>\n(9). Corps.<br>\n(10). Dancer.<br>\n(11). Dessert.<br>\n(12). Dutch.<br>\n(13). Easily.<br>\n(14). Enough.<br>\n(15). Ewe.<br>\n(16). Fare.<br>\n(17). Feinting.<br>\n(18). File.<br>\n(19). Four.<br>\n(20). Fowl.<br>\n(21). Gardens.<br>\n(22). Hazel.<br>\n(23). Jacob's.<br>\n(24). Jane.<br>\n(25). Just.<br>\n(26). Knighted:<br>\n(27). Ladder.<br>\n(28). Man.<br>\n(29). Mary.<br>\n(30). Nocturnal.<br>\n(31). Omission.<br>\n(32). Ophuls.<br>\n(33). Order.<br>\n(34). Peri.<br>\n(35). Pie.<br>\n(36). Plain.<br>\n(37). Play.<br>\n(38). Queue.<br>\n(39). Rum.<br>\n(40). Scope.<br>\n(41). Ship.<br>\n(42). Show.<br>\n(43). Slide.<br>\n(44). Spell.<br>\n(45). Suede.<br>\n(46). Swans.<br>\n(47). Tango.<br>\n(48). Tiff.<br>\n(49). Vile.<br>\n(50). Weigh.<br>\n(51). Which.</p> <p>Winners will receive one of the following: the Collector's\nEdition of Thomas H. Middleton's <em>Light Refractions</em> (retail\nvalue, $30 or £15); <em>English English</em> by Norman W. Schur\n(retail value, $24.95 or £12.50); three copies of <em>Wordsmanship</em>,\nby Claurène duGran (retail value, $29.85 or £14.85); twelve\ncopies of <em>Definitive Quotations</em>, by John Ferguson (retail value,\n$35.40 or 18); <em>Word for Word</em>, by Edward C. Pinkerton (retail\nvalue, $39.95 or £20); four one-year subscriptions to VERBATIM\n(retail value, $30 or £15); any two of the follwing: <em>Verbatim\nVolumes I &amp; II, Verbatim Volumes III &amp; IV, Verbatim Volumes\nV &amp; VI, Verbatim Index: Volumes I-VI;</em> or a credit of $25 or\n£12.50 towards the purchase of any other title or titles offered\nin the VERBATIM Book Club Catalogue.</p> <p>Those living in the U.K., Europe, the Middle East, or\nNorth Africa should send their answers to VERBATIM, 2 Market\nSquare, Aylesbury, Bucks, England.  All others should send\nthem to VERBATIM, Essex, CT 06426, U.S.A.</p>"
}